can_data_2024_explorer/__init__.py
can_data_2024_explorer/__main__.py
can_data_2024_explorer/assets/can_description_hsm.pdf
can_data_2024_explorer/assets/co2forit.png
can_data_2024_explorer/assets/iFOS_Logo_klein_transparent.png
can_data_2024_explorer/assets/ifos.mplstyle
can_data_2024_explorer-0.4.3.dist-info/WHEEL
can_data_2024_explorer-0.4.3.dist-info/METADATA
can_data_2024_explorer-0.4.3.dist-info/RECORD
