Metadata-Version: 2.4
Name: can-data-2024-explorer
Version: 0.4.3
Summary: Library for viewing CAN bus data from HSM research machines.
Author-email: Jakub Wolosz <jakub.wolosz@ifos-gmbh.de>, "Lukas J. Schreiber" <lukas.schreiber@ifos-gmbh.de>
Requires-Dist: pandas~=2.1
Requires-Dist: matplotlib~=3.9
Requires-Dist: cantools>=40.1.0
Requires-Dist: setuptools<81
Project-URL: Home, https://www.ifos-gmbh.de
